[{"iob":-0.078,"activity":-0.0009,"bolussnooze":0,"basaliob":-0.078,"netbasalinsulin":-0.3,"hightempinsulin":0.85,"time":"2017-01-11T03:30:32.000Z"},{"iob":-0.125,"activity":-0.0005,"bolussnooze":0,"basaliob":-0.125,"netbasalinsulin":-0.3,"hightempinsulin":0.85,"time":"2017-01-11T03:35:32.000Z"},{"iob":-0.174,"activity":-0.0002,"bolussnooze":0,"basaliob":-0.174,"netbasalinsulin":-0.3,"hightempinsulin":0.85,"time":"2017-01-11T03:40:32.000Z"},{"iob":-0.274,"activity":-0.0001,"bolussnooze":0,"basaliob":-0.274,"netbasalinsulin":-0.35,"hightempinsulin":0.85,"time":"2017-01-11T03:45:32.000Z"},{"iob":-0.324,"activity":-0.0001,"bolussnooze":0,"basaliob":-0.324,"netbasalinsulin":-0.4,"hightempinsulin":0.85,"time":"2017-01-11T03:50:32.000Z"},{"iob":-0.322,"activity":-0.0002,"bolussnooze":0,"basaliob":-0.322,"netbasalinsulin":-0.45,"hightempinsulin":0.8,"time":"2017-01-11T03:55:32.000Z"},{"iob":-0.32,"activity":-0.0004,"bolussnooze":0,"basaliob":-0.32,"netbasalinsulin":-0.5,"hightempinsulin":0.75,"time":"2017-01-11T04:00:32.000Z"},{"iob":-0.317,"activity":-0.0007,"bolussnooze":0,"basaliob":-0.317,"netbasalinsulin":-0.55,"hightempinsulin":0.7,"time":"2017-01-11T04:05:32.000Z"},{"iob":-0.313,"activity":-0.0009,"bolussnooze":0,"basaliob":-0.313,"netbasalinsulin":-0.65,"hightempinsulin":0.6,"time":"2017-01-11T04:10:32.000Z"},{"iob":-0.306,"activity":-0.0013,"bolussnooze":0,"basaliob":-0.306,"netbasalinsulin":-0.7,"hightempinsulin":0.55,"time":"2017-01-11T04:15:32.000Z"},{"iob":-0.298,"activity":-0.0017,"bolussnooze":0,"basaliob":-0.298,"netbasalinsulin":-0.65,"hightempinsulin":0.55,"time":"2017-01-11T04:20:32.000Z"},{"iob":-0.287,"activity":-0.0021,"bolussnooze":0,"basaliob":-0.287,"netbasalinsulin":-0.6,"hightempinsulin":0.55,"time":"2017-01-11T04:25:32.000Z"},{"iob":-0.275,"activity":-0.0024,"bolussnooze":0,"basaliob":-0.275,"netbasalinsulin":-0.5,"hightempinsulin":0.55,"time":"2017-01-11T04:30:32.000Z"},{"iob":-0.262,"activity":-0.0026,"bolussnooze":0,"basaliob":-0.262,"netbasalinsulin":-0.45,"hightempinsulin":0.55,"time":"2017-01-11T04:35:32.000Z"},{"iob":-0.248,"activity":-0.0029,"bolussnooze":0,"basaliob":-0.248,"netbasalinsulin":-0.4,"hightempinsulin":0.55,"time":"2017-01-11T04:40:32.000Z"},{"iob":-0.233,"activity":-0.003,"bolussnooze":0,"basaliob":-0.233,"netbasalinsulin":-0.35,"hightempinsulin":0.55,"time":"2017-01-11T04:45:32.000Z"},{"iob":-0.217,"activity":-0.0032,"bolussnooze":0,"basaliob":-0.217,"netbasalinsulin":-0.3,"hightempinsulin":0.55,"time":"2017-01-11T04:50:32.000Z"},{"iob":-0.201,"activity":-0.0032,"bolussnooze":0,"basaliob":-0.201,"netbasalinsulin":-0.25,"hightempinsulin":0.55,"time":"2017-01-11T04:55:32.000Z"},{"iob":-0.185,"activity":-0.0032,"bolussnooze":0,"basaliob":-0.185,"netbasalinsulin":-0.25,"hightempinsulin":0.55,"time":"2017-01-11T05:00:32.000Z"},{"iob":-0.169,"activity":-0.0031,"bolussnooze":0,"basaliob":-0.169,"netbasalinsulin":-0.15,"hightempinsulin":0.55,"time":"2017-01-11T05:05:32.000Z"},{"iob":-0.154,"activity":-0.0031,"bolussnooze":0,"basaliob":-0.154,"netbasalinsulin":-0.1,"hightempinsulin":0.55,"time":"2017-01-11T05:10:32.000Z"},{"iob":-0.138,"activity":-0.003,"bolussnooze":0,"basaliob":-0.138,"netbasalinsulin":-0.05,"hightempinsulin":0.55,"time":"2017-01-11T05:15:32.000Z"},{"iob":-0.123,"activity":-0.003,"bolussnooze":0,"basaliob":-0.123,"netbasalinsulin":-0.05,"hightempinsulin":0.55,"time":"2017-01-11T05:20:32.000Z"},{"iob":-0.108,"activity":-0.003,"bolussnooze":0,"basaliob":-0.108,"netbasalinsulin":-0.1,"hightempinsulin":0.5,"time":"2017-01-11T05:25:32.000Z"},{"iob":-0.094,"activity":-0.0029,"bolussnooze":0,"basaliob":-0.094,"netbasalinsulin":-0.15,"hightempinsulin":0.45,"time":"2017-01-11T05:30:32.000Z"},{"iob":-0.08,"activity":-0.0028,"bolussnooze":0,"basaliob":-0.08,"netbasalinsulin":-0.25,"hightempinsulin":0.35,"time":"2017-01-11T05:35:32.000Z"},{"iob":-0.067,"activity":-0.0027,"bolussnooze":0,"basaliob":-0.067,"netbasalinsulin":-0.3,"hightempinsulin":0.3,"time":"2017-01-11T05:40:32.000Z"},{"iob":-0.054,"activity":-0.0025,"bolussnooze":0,"basaliob":-0.054,"netbasalinsulin":-0.4,"hightempinsulin":0.2,"time":"2017-01-11T05:45:32.000Z"},{"iob":-0.043,"activity":-0.0023,"bolussnooze":0,"basaliob":-0.043,"netbasalinsulin":-0.45,"hightempinsulin":0.15,"time":"2017-01-11T05:50:32.000Z"},{"iob":-0.033,"activity":-0.002,"bolussnooze":0,"basaliob":-0.033,"netbasalinsulin":-0.55,"hightempinsulin":0.05,"time":"2017-01-11T05:55:32.000Z"},{"iob":-0.024,"activity":-0.0017,"bolussnooze":0,"basaliob":-0.024,"netbasalinsulin":-0.6,"hightempinsulin":0,"time":"2017-01-11T06:00:32.000Z"},{"iob":-0.018,"activity":-0.0014,"bolussnooze":0,"basaliob":-0.018,"netbasalinsulin":-0.55,"hightempinsulin":0,"time":"2017-01-11T06:05:32.000Z"},{"iob":-0.012,"activity":-0.0011,"bolussnooze":0,"basaliob":-0.012,"netbasalinsulin":-0.5,"hightempinsulin":0,"time":"2017-01-11T06:10:32.000Z"},{"iob":-0.008,"activity":-0.0009,"bolussnooze":0,"basaliob":-0.008,"netbasalinsulin":-0.45,"hightempinsulin":0,"time":"2017-01-11T06:15:32.000Z"},{"iob":-0.005,"activity":-0.0006,"bolussnooze":0,"basaliob":-0.005,"netbasalinsulin":-0.4,"hightempinsulin":0,"time":"2017-01-11T06:20:32.000Z"},{"iob":-0.002,"activity":-0.0004,"bolussnooze":0,"basaliob":-0.002,"netbasalinsulin":-0.35,"hightempinsulin":0,"time":"2017-01-11T06:25:32.000Z"},{"iob":-0.001,"activity":-0.0003,"bolussnooze":0,"basaliob":-0.001,"netbasalinsulin":-0.25,"hightempinsulin":0,"time":"2017-01-11T06:30:32.000Z"},{"iob":0,"activity":-0.0002,"bolussnooze":0,"basaliob":0,"netbasalinsulin":-0.2,"hightempinsulin":0,"time":"2017-01-11T06:35:32.000Z"},{"iob":0,"activity":-0.0001,"bolussnooze":0,"basaliob":0,"netbasalinsulin":-0.15,"hightempinsulin":0,"time":"2017-01-11T06:40:32.000Z"},{"iob":0,"activity":0,"bolussnooze":0,"basaliob":0,"netbasalinsulin":-0.05,"hightempinsulin":0,"time":"2017-01-11T06:45:32.000Z"},{"iob":0,"activity":0,"bolussnooze":0,"basaliob":0,"netbasalinsulin":0,"hightempinsulin":0,"time":"2017-01-11T06:50:32.000Z"},{"iob":0,"activity":0,"bolussnooze":0,"basaliob":0,"netbasalinsulin":0,"hightempinsulin":0,"time":"2017-01-11T06:55:32.000Z"}]
