[{"iob":1.996,"activity":0.0108,"bolussnooze":0.291,"basaliob":1.631,"netbasalinsulin":1.65,"hightempinsulin":1.85,"time":"2017-02-28T02:46:54.000Z"},{"iob":2.135,"activity":0.0122,"bolussnooze":0.28,"basaliob":1.785,"netbasalinsulin":1.85,"hightempinsulin":2.05,"time":"2017-02-28T02:51:54.000Z"},{"iob":2.217,"activity":0.0137,"bolussnooze":0.264,"basaliob":1.883,"netbasalinsulin":2,"hightempinsulin":2.2,"time":"2017-02-28T02:56:54.000Z"},{"iob":2.341,"activity":0.0152,"bolussnooze":0.244,"basaliob":2.022,"netbasalinsulin":2.2,"hightempinsulin":2.4,"time":"2017-02-28T03:01:54.000Z"},{"iob":2.456,"activity":0.0169,"bolussnooze":0.219,"basaliob":2.153,"netbasalinsulin":2.45,"hightempinsulin":2.6,"time":"2017-02-28T03:06:54.000Z"},{"iob":2.513,"activity":0.0186,"bolussnooze":0.19,"basaliob":2.225,"netbasalinsulin":2.65,"hightempinsulin":2.75,"time":"2017-02-28T03:11:54.000Z"},{"iob":2.413,"activity":0.0201,"bolussnooze":0.158,"basaliob":2.139,"netbasalinsulin":2.65,"hightempinsulin":2.75,"time":"2017-02-28T03:16:54.000Z"},{"iob":2.305,"activity":0.0215,"bolussnooze":0.128,"basaliob":2.046,"netbasalinsulin":2.7,"hightempinsulin":2.75,"time":"2017-02-28T03:21:54.000Z"},{"iob":2.192,"activity":0.0227,"bolussnooze":0.101,"basaliob":1.947,"netbasalinsulin":2.75,"hightempinsulin":2.75,"time":"2017-02-28T03:26:54.000Z"},{"iob":2.073,"activity":0.0236,"bolussnooze":0.077,"basaliob":1.843,"netbasalinsulin":2.75,"hightempinsulin":2.75,"time":"2017-02-28T03:31:54.000Z"},{"iob":1.951,"activity":0.0245,"bolussnooze":0.056,"basaliob":1.735,"netbasalinsulin":2.75,"hightempinsulin":2.75,"time":"2017-02-28T03:36:54.000Z"},{"iob":1.825,"activity":0.0252,"bolussnooze":0.039,"basaliob":1.623,"netbasalinsulin":2.75,"hightempinsulin":2.75,"time":"2017-02-28T03:41:54.000Z"},{"iob":1.695,"activity":0.0259,"bolussnooze":0.025,"basaliob":1.509,"netbasalinsulin":2.75,"hightempinsulin":2.75,"time":"2017-02-28T03:46:54.000Z"},{"iob":1.564,"activity":0.0263,"bolussnooze":0.014,"basaliob":1.393,"netbasalinsulin":2.75,"hightempinsulin":2.75,"time":"2017-02-28T03:51:54.000Z"},{"iob":1.432,"activity":0.0263,"bolussnooze":0.006,"basaliob":1.278,"netbasalinsulin":2.75,"hightempinsulin":2.75,"time":"2017-02-28T03:56:54.000Z"},{"iob":1.302,"activity":0.0259,"bolussnooze":0.001,"basaliob":1.163,"netbasalinsulin":2.75,"hightempinsulin":2.75,"time":"2017-02-28T04:01:54.000Z"},{"iob":1.175,"activity":0.0254,"bolussnooze":0,"basaliob":1.051,"netbasalinsulin":2.75,"hightempinsulin":2.75,"time":"2017-02-28T04:06:54.000Z"},{"iob":1.052,"activity":0.0245,"bolussnooze":0,"basaliob":0.941,"netbasalinsulin":2.75,"hightempinsulin":2.75,"time":"2017-02-28T04:11:54.000Z"},{"iob":0.935,"activity":0.0235,"bolussnooze":0,"basaliob":0.837,"netbasalinsulin":2.75,"hightempinsulin":2.75,"time":"2017-02-28T04:16:54.000Z"},{"iob":0.824,"activity":0.0222,"bolussnooze":0,"basaliob":0.738,"netbasalinsulin":2.7,"hightempinsulin":2.7,"time":"2017-02-28T04:21:54.000Z"},{"iob":0.72,"activity":0.0207,"bolussnooze":0,"basaliob":0.645,"netbasalinsulin":2.65,"hightempinsulin":2.65,"time":"2017-02-28T04:26:54.000Z"},{"iob":0.624,"activity":0.0192,"bolussnooze":0,"basaliob":0.56,"netbasalinsulin":2.65,"hightempinsulin":2.65,"time":"2017-02-28T04:31:54.000Z"},{"iob":0.536,"activity":0.0176,"bolussnooze":0,"basaliob":0.481,"netbasalinsulin":2.6,"hightempinsulin":2.6,"time":"2017-02-28T04:36:54.000Z"},{"iob":0.455,"activity":0.0161,"bolussnooze":0,"basaliob":0.41,"netbasalinsulin":2.6,"hightempinsulin":2.6,"time":"2017-02-28T04:41:54.000Z"},{"iob":0.383,"activity":0.0146,"bolussnooze":0,"basaliob":0.345,"netbasalinsulin":2.6,"hightempinsulin":2.6,"time":"2017-02-28T04:46:54.000Z"},{"iob":0.318,"activity":0.013,"bolussnooze":0,"basaliob":0.287,"netbasalinsulin":2.5,"hightempinsulin":2.5,"time":"2017-02-28T04:51:54.000Z"},{"iob":0.26,"activity":0.0116,"bolussnooze":0,"basaliob":0.236,"netbasalinsulin":2.45,"hightempinsulin":2.45,"time":"2017-02-28T04:56:54.000Z"},{"iob":0.209,"activity":0.0101,"bolussnooze":0,"basaliob":0.191,"netbasalinsulin":2.3,"hightempinsulin":2.3,"time":"2017-02-28T05:01:54.000Z"},{"iob":0.165,"activity":0.0088,"bolussnooze":0,"basaliob":0.152,"netbasalinsulin":2.15,"hightempinsulin":2.15,"time":"2017-02-28T05:06:54.000Z"},{"iob":0.127,"activity":0.0075,"bolussnooze":0,"basaliob":0.119,"netbasalinsulin":2,"hightempinsulin":2,"time":"2017-02-28T05:11:54.000Z"},{"iob":0.096,"activity":0.0064,"bolussnooze":0,"basaliob":0.09,"netbasalinsulin":1.9,"hightempinsulin":1.9,"time":"2017-02-28T05:16:54.000Z"},{"iob":0.07,"activity":0.0052,"bolussnooze":0,"basaliob":0.067,"netbasalinsulin":1.75,"hightempinsulin":1.75,"time":"2017-02-28T05:21:54.000Z"},{"iob":0.049,"activity":0.0042,"bolussnooze":0,"basaliob":0.048,"netbasalinsulin":1.6,"hightempinsulin":1.6,"time":"2017-02-28T05:26:54.000Z"},{"iob":0.033,"activity":0.0032,"bolussnooze":0,"basaliob":0.033,"netbasalinsulin":1.4,"hightempinsulin":1.4,"time":"2017-02-28T05:31:54.000Z"},{"iob":0.021,"activity":0.0024,"bolussnooze":0,"basaliob":0.021,"netbasalinsulin":1.25,"hightempinsulin":1.25,"time":"2017-02-28T05:36:54.000Z"},{"iob":0.013,"activity":0.0017,"bolussnooze":0,"basaliob":0.013,"netbasalinsulin":1.1,"hightempinsulin":1.1,"time":"2017-02-28T05:41:54.000Z"},{"iob":0.007,"activity":0.0012,"bolussnooze":0,"basaliob":0.007,"netbasalinsulin":0.9,"hightempinsulin":0.9,"time":"2017-02-28T05:46:54.000Z"},{"iob":0.003,"activity":0.0007,"bolussnooze":0,"basaliob":0.003,"netbasalinsulin":0.7,"hightempinsulin":0.7,"time":"2017-02-28T05:51:54.000Z"},{"iob":0.001,"activity":0.0004,"bolussnooze":0,"basaliob":0.001,"netbasalinsulin":0.55,"hightempinsulin":0.55,"time":"2017-02-28T05:56:54.000Z"},{"iob":0,"activity":0.0002,"bolussnooze":0,"basaliob":0,"netbasalinsulin":0.35,"hightempinsulin":0.35,"time":"2017-02-28T06:01:54.000Z"},{"iob":0,"activity":0,"bolussnooze":0,"basaliob":0,"netbasalinsulin":0.15,"hightempinsulin":0.15,"time":"2017-02-28T06:06:54.000Z"},{"iob":0,"activity":0,"bolussnooze":0,"basaliob":0,"netbasalinsulin":0,"hightempinsulin":0,"time":"2017-02-28T06:11:54.000Z"}]
