[{"iob":0.554,"activity":0.0108,"bolussnooze":0.023,"basaliob":0.035,"netbasalinsulin":-0.25,"hightempinsulin":0.2,"time":"2017-02-23T19:05:48.000Z"},{"iob":0.502,"activity":0.0104,"bolussnooze":0.006,"basaliob":0.034,"netbasalinsulin":-0.25,"hightempinsulin":0.2,"time":"2017-02-23T19:10:48.000Z"},{"iob":0.452,"activity":0.01,"bolussnooze":0,"basaliob":0.032,"netbasalinsulin":-0.25,"hightempinsulin":0.2,"time":"2017-02-23T19:15:48.000Z"},{"iob":0.404,"activity":0.0096,"bolussnooze":0,"basaliob":0.03,"netbasalinsulin":-0.2,"hightempinsulin":0.2,"time":"2017-02-23T19:20:48.000Z"},{"iob":0.359,"activity":0.0092,"bolussnooze":0,"basaliob":0.028,"netbasalinsulin":-0.15,"hightempinsulin":0.2,"time":"2017-02-23T19:25:48.000Z"},{"iob":0.315,"activity":0.0087,"bolussnooze":0,"basaliob":0.025,"netbasalinsulin":-0.1,"hightempinsulin":0.2,"time":"2017-02-23T19:30:48.000Z"},{"iob":0.274,"activity":0.0082,"bolussnooze":0,"basaliob":0.021,"netbasalinsulin":-0.05,"hightempinsulin":0.2,"time":"2017-02-23T19:35:48.000Z"},{"iob":0.235,"activity":0.0077,"bolussnooze":0,"basaliob":0.018,"netbasalinsulin":0,"hightempinsulin":0.2,"time":"2017-02-23T19:40:48.000Z"},{"iob":0.2,"activity":0.0072,"bolussnooze":0,"basaliob":0.015,"netbasalinsulin":0.05,"hightempinsulin":0.2,"time":"2017-02-23T19:45:48.000Z"},{"iob":0.166,"activity":0.0066,"bolussnooze":0,"basaliob":0.012,"netbasalinsulin":0.1,"hightempinsulin":0.2,"time":"2017-02-23T19:50:48.000Z"},{"iob":0.136,"activity":0.006,"bolussnooze":0,"basaliob":0.009,"netbasalinsulin":0.15,"hightempinsulin":0.2,"time":"2017-02-23T19:55:48.000Z"},{"iob":0.109,"activity":0.0054,"bolussnooze":0,"basaliob":0.006,"netbasalinsulin":0.15,"hightempinsulin":0.2,"time":"2017-02-23T20:00:48.000Z"},{"iob":0.085,"activity":0.0048,"bolussnooze":0,"basaliob":0.004,"netbasalinsulin":0.15,"hightempinsulin":0.2,"time":"2017-02-23T20:05:48.000Z"},{"iob":0.064,"activity":0.0042,"bolussnooze":0,"basaliob":0.002,"netbasalinsulin":0.15,"hightempinsulin":0.2,"time":"2017-02-23T20:10:48.000Z"},{"iob":0.046,"activity":0.0036,"bolussnooze":0,"basaliob":0.001,"netbasalinsulin":0.15,"hightempinsulin":0.2,"time":"2017-02-23T20:15:48.000Z"},{"iob":0.031,"activity":0.003,"bolussnooze":0,"basaliob":0,"netbasalinsulin":0.15,"hightempinsulin":0.2,"time":"2017-02-23T20:20:48.000Z"},{"iob":0.019,"activity":0.0024,"bolussnooze":0,"basaliob":0,"netbasalinsulin":0.15,"hightempinsulin":0.2,"time":"2017-02-23T20:25:48.000Z"},{"iob":0.01,"activity":0.0018,"bolussnooze":0,"basaliob":0,"netbasalinsulin":0.1,"hightempinsulin":0.15,"time":"2017-02-23T20:30:48.000Z"},{"iob":0.004,"activity":0.0012,"bolussnooze":0,"basaliob":0,"netbasalinsulin":0.05,"hightempinsulin":0.1,"time":"2017-02-23T20:35:48.000Z"},{"iob":0.001,"activity":0.0007,"bolussnooze":0,"basaliob":0,"netbasalinsulin":0,"hightempinsulin":0.05,"time":"2017-02-23T20:40:48.000Z"},{"iob":0,"activity":0.0002,"bolussnooze":0,"basaliob":0,"netbasalinsulin":-0.05,"hightempinsulin":0,"time":"2017-02-23T20:45:48.000Z"},{"iob":0,"activity":0,"bolussnooze":0,"basaliob":0,"netbasalinsulin":0,"hightempinsulin":0,"time":"2017-02-23T20:50:48.000Z"},{"iob":0,"activity":0,"bolussnooze":0,"basaliob":0,"netbasalinsulin":0,"hightempinsulin":0,"time":"2017-02-23T20:55:48.000Z"},{"iob":0,"activity":0,"bolussnooze":0,"basaliob":0,"netbasalinsulin":0,"hightempinsulin":0,"time":"2017-02-23T21:00:48.000Z"},{"iob":0,"activity":0,"bolussnooze":0,"basaliob":0,"netbasalinsulin":0,"hightempinsulin":0,"time":"2017-02-23T21:05:48.000Z"},{"iob":0,"activity":0,"bolussnooze":0,"basaliob":0,"netbasalinsulin":0,"hightempinsulin":0,"time":"2017-02-23T21:10:48.000Z"},{"iob":0,"activity":0,"bolussnooze":0,"basaliob":0,"netbasalinsulin":0,"hightempinsulin":0,"time":"2017-02-23T21:15:48.000Z"},{"iob":0,"activity":0,"bolussnooze":0,"basaliob":0,"netbasalinsulin":0,"hightempinsulin":0,"time":"2017-02-23T21:20:48.000Z"},{"iob":0,"activity":0,"bolussnooze":0,"basaliob":0,"netbasalinsulin":0,"hightempinsulin":0,"time":"2017-02-23T21:25:48.000Z"},{"iob":0,"activity":0,"bolussnooze":0,"basaliob":0,"netbasalinsulin":0,"hightempinsulin":0,"time":"2017-02-23T21:30:48.000Z"},{"iob":0,"activity":0,"bolussnooze":0,"basaliob":0,"netbasalinsulin":0,"hightempinsulin":0,"time":"2017-02-23T21:35:48.000Z"},{"iob":0,"activity":0,"bolussnooze":0,"basaliob":0,"netbasalinsulin":0,"hightempinsulin":0,"time":"2017-02-23T21:40:48.000Z"},{"iob":0,"activity":0,"bolussnooze":0,"basaliob":0,"netbasalinsulin":0,"hightempinsulin":0,"time":"2017-02-23T21:45:48.000Z"},{"iob":0,"activity":0,"bolussnooze":0,"basaliob":0,"netbasalinsulin":0,"hightempinsulin":0,"time":"2017-02-23T21:50:48.000Z"},{"iob":0,"activity":0,"bolussnooze":0,"basaliob":0,"netbasalinsulin":0,"hightempinsulin":0,"time":"2017-02-23T21:55:48.000Z"},{"iob":0,"activity":0,"bolussnooze":0,"basaliob":0,"netbasalinsulin":0,"hightempinsulin":0,"time":"2017-02-23T22:00:48.000Z"},{"iob":0,"activity":0,"bolussnooze":0,"basaliob":0,"netbasalinsulin":0,"hightempinsulin":0,"time":"2017-02-23T22:05:48.000Z"},{"iob":0,"activity":0,"bolussnooze":0,"basaliob":0,"netbasalinsulin":0,"hightempinsulin":0,"time":"2017-02-23T22:10:48.000Z"},{"iob":0,"activity":0,"bolussnooze":0,"basaliob":0,"netbasalinsulin":0,"hightempinsulin":0,"time":"2017-02-23T22:15:48.000Z"},{"iob":0,"activity":0,"bolussnooze":0,"basaliob":0,"netbasalinsulin":0,"hightempinsulin":0,"time":"2017-02-23T22:20:48.000Z"},{"iob":0,"activity":0,"bolussnooze":0,"basaliob":0,"netbasalinsulin":0,"hightempinsulin":0,"time":"2017-02-23T22:25:48.000Z"},{"iob":0,"activity":0,"bolussnooze":0,"basaliob":0,"netbasalinsulin":0,"hightempinsulin":0,"time":"2017-02-23T22:30:48.000Z"}]
