[{"iob":-0.018,"activity":0.0019,"bolussnooze":0,"basaliob":-0.018,"netbasalinsulin":0.45,"hightempinsulin":0.65,"time":"2017-01-30T03:10:39.000Z"},{"iob":-0.076,"activity":0.0016,"bolussnooze":0,"basaliob":-0.076,"netbasalinsulin":0.3,"hightempinsulin":0.55,"time":"2017-01-30T03:15:39.000Z"},{"iob":-0.132,"activity":0.0013,"bolussnooze":0,"basaliob":-0.132,"netbasalinsulin":0.2,"hightempinsulin":0.5,"time":"2017-01-30T03:20:39.000Z"},{"iob":-0.187,"activity":0.001,"bolussnooze":0,"basaliob":-0.187,"netbasalinsulin":0.15,"hightempinsulin":0.5,"time":"2017-01-30T03:25:39.000Z"},{"iob":-0.291,"activity":0.0007,"bolussnooze":0,"basaliob":-0.291,"netbasalinsulin":0,"hightempinsulin":0.45,"time":"2017-01-30T03:30:39.000Z"},{"iob":-0.342,"activity":0.0003,"bolussnooze":0,"basaliob":-0.342,"netbasalinsulin":-0.15,"hightempinsulin":0.35,"time":"2017-01-30T03:35:39.000Z"},{"iob":-0.342,"activity":-0.0001,"bolussnooze":0,"basaliob":-0.342,"netbasalinsulin":-0.2,"hightempinsulin":0.3,"time":"2017-01-30T03:40:39.000Z"},{"iob":-0.339,"activity":-0.0005,"bolussnooze":0,"basaliob":-0.339,"netbasalinsulin":-0.2,"hightempinsulin":0.3,"time":"2017-01-30T03:45:39.000Z"},{"iob":-0.334,"activity":-0.0009,"bolussnooze":0,"basaliob":-0.334,"netbasalinsulin":-0.2,"hightempinsulin":0.3,"time":"2017-01-30T03:50:39.000Z"},{"iob":-0.328,"activity":-0.0013,"bolussnooze":0,"basaliob":-0.328,"netbasalinsulin":-0.2,"hightempinsulin":0.3,"time":"2017-01-30T03:55:39.000Z"},{"iob":-0.319,"activity":-0.0017,"bolussnooze":0,"basaliob":-0.319,"netbasalinsulin":-0.2,"hightempinsulin":0.3,"time":"2017-01-30T04:00:39.000Z"},{"iob":-0.309,"activity":-0.0021,"bolussnooze":0,"basaliob":-0.309,"netbasalinsulin":-0.2,"hightempinsulin":0.3,"time":"2017-01-30T04:05:39.000Z"},{"iob":-0.296,"activity":-0.0025,"bolussnooze":0,"basaliob":-0.296,"netbasalinsulin":-0.2,"hightempinsulin":0.3,"time":"2017-01-30T04:10:39.000Z"},{"iob":-0.282,"activity":-0.0029,"bolussnooze":0,"basaliob":-0.282,"netbasalinsulin":-0.2,"hightempinsulin":0.3,"time":"2017-01-30T04:15:39.000Z"},{"iob":-0.266,"activity":-0.0032,"bolussnooze":0,"basaliob":-0.266,"netbasalinsulin":-0.2,"hightempinsulin":0.3,"time":"2017-01-30T04:20:39.000Z"},{"iob":-0.248,"activity":-0.0035,"bolussnooze":0,"basaliob":-0.248,"netbasalinsulin":-0.25,"hightempinsulin":0.25,"time":"2017-01-30T04:25:39.000Z"},{"iob":-0.229,"activity":-0.0037,"bolussnooze":0,"basaliob":-0.229,"netbasalinsulin":-0.3,"hightempinsulin":0.2,"time":"2017-01-30T04:30:39.000Z"},{"iob":-0.21,"activity":-0.0038,"bolussnooze":0,"basaliob":-0.21,"netbasalinsulin":-0.35,"hightempinsulin":0.15,"time":"2017-01-30T04:35:39.000Z"},{"iob":-0.191,"activity":-0.0038,"bolussnooze":0,"basaliob":-0.191,"netbasalinsulin":-0.4,"hightempinsulin":0.1,"time":"2017-01-30T04:40:39.000Z"},{"iob":-0.172,"activity":-0.0037,"bolussnooze":0,"basaliob":-0.172,"netbasalinsulin":-0.4,"hightempinsulin":0.1,"time":"2017-01-30T04:45:39.000Z"},{"iob":-0.155,"activity":-0.0036,"bolussnooze":0,"basaliob":-0.155,"netbasalinsulin":-0.4,"hightempinsulin":0.1,"time":"2017-01-30T04:50:39.000Z"},{"iob":-0.138,"activity":-0.0034,"bolussnooze":0,"basaliob":-0.138,"netbasalinsulin":-0.4,"hightempinsulin":0.1,"time":"2017-01-30T04:55:39.000Z"},{"iob":-0.122,"activity":-0.0032,"bolussnooze":0,"basaliob":-0.122,"netbasalinsulin":-0.35,"hightempinsulin":0.1,"time":"2017-01-30T05:00:39.000Z"},{"iob":-0.107,"activity":-0.003,"bolussnooze":0,"basaliob":-0.107,"netbasalinsulin":-0.3,"hightempinsulin":0.1,"time":"2017-01-30T05:05:39.000Z"},{"iob":-0.093,"activity":-0.0028,"bolussnooze":0,"basaliob":-0.093,"netbasalinsulin":-0.35,"hightempinsulin":0.05,"time":"2017-01-30T05:10:39.000Z"},{"iob":-0.08,"activity":-0.0026,"bolussnooze":0,"basaliob":-0.08,"netbasalinsulin":-0.35,"hightempinsulin":0.05,"time":"2017-01-30T05:15:39.000Z"},{"iob":-0.068,"activity":-0.0024,"bolussnooze":0,"basaliob":-0.068,"netbasalinsulin":-0.35,"hightempinsulin":0.05,"time":"2017-01-30T05:20:39.000Z"},{"iob":-0.056,"activity":-0.0022,"bolussnooze":0,"basaliob":-0.056,"netbasalinsulin":-0.4,"hightempinsulin":0,"time":"2017-01-30T05:25:39.000Z"},{"iob":-0.046,"activity":-0.002,"bolussnooze":0,"basaliob":-0.046,"netbasalinsulin":-0.4,"hightempinsulin":0,"time":"2017-01-30T05:30:39.000Z"},{"iob":-0.037,"activity":-0.0018,"bolussnooze":0,"basaliob":-0.037,"netbasalinsulin":-0.4,"hightempinsulin":0,"time":"2017-01-30T05:35:39.000Z"},{"iob":-0.029,"activity":-0.0016,"bolussnooze":0,"basaliob":-0.029,"netbasalinsulin":-0.4,"hightempinsulin":0,"time":"2017-01-30T05:40:39.000Z"},{"iob":-0.022,"activity":-0.0014,"bolussnooze":0,"basaliob":-0.022,"netbasalinsulin":-0.4,"hightempinsulin":0,"time":"2017-01-30T05:45:39.000Z"},{"iob":-0.016,"activity":-0.0012,"bolussnooze":0,"basaliob":-0.016,"netbasalinsulin":-0.4,"hightempinsulin":0,"time":"2017-01-30T05:50:39.000Z"},{"iob":-0.011,"activity":-0.001,"bolussnooze":0,"basaliob":-0.011,"netbasalinsulin":-0.4,"hightempinsulin":0,"time":"2017-01-30T05:55:39.000Z"},{"iob":-0.008,"activity":-0.0008,"bolussnooze":0,"basaliob":-0.008,"netbasalinsulin":-0.35,"hightempinsulin":0,"time":"2017-01-30T06:00:39.000Z"},{"iob":-0.005,"activity":-0.0006,"bolussnooze":0,"basaliob":-0.005,"netbasalinsulin":-0.35,"hightempinsulin":0,"time":"2017-01-30T06:05:39.000Z"},{"iob":-0.003,"activity":-0.0004,"bolussnooze":0,"basaliob":-0.003,"netbasalinsulin":-0.3,"hightempinsulin":0,"time":"2017-01-30T06:10:39.000Z"},{"iob":-0.001,"activity":-0.0003,"bolussnooze":0,"basaliob":-0.001,"netbasalinsulin":-0.25,"hightempinsulin":0,"time":"2017-01-30T06:15:39.000Z"},{"iob":0,"activity":-0.0002,"bolussnooze":0,"basaliob":0,"netbasalinsulin":-0.2,"hightempinsulin":0,"time":"2017-01-30T06:20:39.000Z"},{"iob":0,"activity":-0.0001,"bolussnooze":0,"basaliob":0,"netbasalinsulin":-0.15,"hightempinsulin":0,"time":"2017-01-30T06:25:39.000Z"},{"iob":0,"activity":0,"bolussnooze":0,"basaliob":0,"netbasalinsulin":-0.05,"hightempinsulin":0,"time":"2017-01-30T06:30:39.000Z"},{"iob":0,"activity":0,"bolussnooze":0,"basaliob":0,"netbasalinsulin":0,"hightempinsulin":0,"time":"2017-01-30T06:35:39.000Z"}]
