{
  "bg": 64, 
  "temp": "absolute", 
  "snoozeBG": 84, 
  "predBGs": {
    "IOB": [
      64, 
      63, 
      62, 
      61, 
      61, 
      62, 
      62, 
      63, 
      65, 
      67, 
      69, 
      71, 
      74, 
      78, 
      81, 
      84, 
      87, 
      91, 
      94, 
      98, 
      101, 
      104, 
      107, 
      110, 
      113, 
      115, 
      117, 
      119, 
      121, 
      122, 
      124, 
      125, 
      126, 
      127, 
      128, 
      128, 
      129, 
      129, 
      129, 
      130
    ]
  }, 
  "reason": "COB: 0, Dev: -22, BGI: 2.08, ISF: 83, Target: 97; BG 64<74, but 28m left and 0 ~ req 0U/hr: no action required", 
  "COB": 0, 
  "eventualBG": 84, 
  "tick": "+0", 
  "IOB": -0.507
}