{
  "bg": 155, 
  "temp": "absolute", 
  "snoozeBG": 146, 
  "predBGs": {
    "COB": [
      155, 
      158, 
      161, 
      162, 
      161, 
      160, 
      157, 
      152, 
      147, 
      142, 
      137, 
      132, 
      128, 
      123, 
      118, 
      114, 
      109, 
      105, 
      100, 
      96, 
      92, 
      88, 
      85, 
      81, 
      78, 
      75, 
      73, 
      70, 
      68, 
      66, 
      65, 
      63, 
      62, 
      61, 
      60, 
      60, 
      59
    ], 
    "aCOB": [
      155, 
      157, 
      159, 
      159, 
      159, 
      158, 
      156, 
      152, 
      148, 
      143, 
      138, 
      133, 
      128, 
      124, 
      119, 
      115, 
      110, 
      106, 
      101, 
      97, 
      93, 
      89, 
      85, 
      82, 
      79, 
      76, 
      74, 
      71, 
      69, 
      67, 
      65, 
      64, 
      63, 
      62, 
      61, 
      60, 
      60, 
      60, 
      60, 
      60, 
      59
    ], 
    "IOB": [
      155, 
      159, 
      162, 
      165, 
      167, 
      169, 
      169, 
      169, 
      168, 
      165, 
      162, 
      159, 
      154, 
      149, 
      144, 
      140, 
      136, 
      131, 
      127, 
      122, 
      118, 
      114, 
      111, 
      108, 
      105, 
      102, 
      99, 
      97, 
      95, 
      93, 
      91, 
      90, 
      88, 
      87, 
      87, 
      86, 
      86, 
      85
    ]
  }, 
  "reason": "COB: 5, Dev: 69, BGI: -6.5, ISF: 82, Target: 80; Eventual BG 146 >= 80, temp 2.25 >~ req 2.25U/hr", 
  "COB": 5, 
  "eventualBG": 146, 
  "tick": "+5", 
  "IOB": 0.95
}