{
  "bg": 56, 
  "temp": "absolute", 
  "snoozeBG": 32, 
  "predBGs": {
    "aCOB": [
      56, 
      60, 
      65, 
      70, 
      76, 
      81, 
      88, 
      94, 
      101, 
      108, 
      116, 
      124, 
      132, 
      140, 
      148, 
      157, 
      165, 
      173, 
      182, 
      189, 
      197, 
      205, 
      212, 
      218, 
      225, 
      231, 
      237, 
      242, 
      247, 
      252, 
      257, 
      261, 
      265, 
      268, 
      271, 
      274, 
      277, 
      279, 
      281, 
      282, 
      283, 
      285
    ], 
    "IOB": [
      56, 
      51, 
      46, 
      42, 
      39, 
      39, 
      39, 
      39, 
      39, 
      39, 
      39, 
      39, 
      39, 
      39, 
      39, 
      39, 
      39, 
      39, 
      39, 
      41, 
      43, 
      45, 
      47, 
      48, 
      50, 
      52, 
      53, 
      54, 
      56, 
      57, 
      58, 
      59, 
      59, 
      60, 
      61, 
      61, 
      61, 
      62
    ]
  }, 
  "rate": 0, 
  "reason": "COB: 27, Dev: -12, BGI: -3.6, ISF: 82, Target: 96; BG 56<73", 
  "COB": 27, 
  "eventualBG": 32, 
  "duration": 30, 
  "tick": -3, 
  "IOB": 0.151
}