{
  "bg": 165, 
  "temp": "absolute", 
  "snoozeBG": 81, 
  "predBGs": {
    "IOB": [
      165, 
      165, 
      165, 
      163, 
      161, 
      158, 
      155, 
      151, 
      146, 
      141, 
      135, 
      129, 
      122, 
      116, 
      110, 
      105, 
      100, 
      95, 
      91, 
      87, 
      84, 
      81, 
      79, 
      76, 
      75, 
      73, 
      72, 
      71, 
      70, 
      69
    ]
  }, 
  "reason": "COB: 0, Dev: 53, BGI: -7.83, ISF: 83, Target: 80; Eventual BG 81 >= 80, temp 1 >~ req 1U/hr", 
  "COB": 0, 
  "eventualBG": 81, 
  "tick": "+2", 
  "IOB": 1.643
}