{
  "bg": 156, 
  "temp": "absolute", 
  "snoozeBG": 176, 
  "predBGs": {
    "COB": [
      156, 
      164, 
      170, 
      176, 
      180, 
      182, 
      184, 
      185, 
      186, 
      187, 
      187, 
      187, 
      186, 
      185, 
      184, 
      183, 
      181, 
      180, 
      178, 
      177, 
      177, 
      176, 
      176, 
      177, 
      177, 
      178, 
      180, 
      182, 
      183, 
      185, 
      187, 
      188, 
      190, 
      191, 
      193, 
      194, 
      196, 
      197, 
      198, 
      199
    ], 
    "aCOB": [
      156, 
      161, 
      164, 
      167, 
      168, 
      168, 
      167, 
      166, 
      165, 
      163, 
      162, 
      160, 
      157, 
      155, 
      152, 
      150, 
      147, 
      145, 
      143, 
      141, 
      140, 
      139, 
      139, 
      139, 
      140, 
      141, 
      143, 
      145, 
      147, 
      150, 
      152, 
      155, 
      158, 
      161, 
      164, 
      167, 
      170, 
      173, 
      176, 
      179, 
      181, 
      184, 
      186
    ], 
    "IOB": [
      156, 
      163, 
      168, 
      171, 
      172, 
      171, 
      168, 
      163, 
      158, 
      151, 
      144, 
      135, 
      125, 
      114, 
      104, 
      95, 
      85, 
      76, 
      67, 
      59, 
      51, 
      44, 
      39
    ]
  }, 
  "reason": "COB: 28, Dev: 80, BGI: -5.26, ISF: 95, Target: 102; Eventual BG 199 >= 102, temp 2.75 >~ req 2.4U/hr", 
  "COB": 28, 
  "eventualBG": 199, 
  "tick": "+8", 
  "IOB": 1.734
}