{
  "bg": 137, 
  "temp": "absolute", 
  "snoozeBG": 96, 
  "predBGs": {
    "COB": [
      137, 
      131, 
      126, 
      120, 
      113, 
      106, 
      100, 
      93, 
      86, 
      79, 
      73, 
      68, 
      64, 
      60, 
      58, 
      56, 
      56, 
      55, 
      56, 
      57, 
      59, 
      61, 
      64, 
      67, 
      71, 
      75, 
      80, 
      85, 
      90, 
      96, 
      102, 
      108, 
      114, 
      120, 
      126, 
      132, 
      137, 
      143, 
      149, 
      155, 
      160, 
      166, 
      172
    ], 
    "aCOB": [
      137, 
      134, 
      131, 
      128, 
      124, 
      120, 
      116, 
      111, 
      107, 
      102, 
      99, 
      96, 
      94, 
      94, 
      93, 
      94, 
      96, 
      98, 
      100, 
      104, 
      108, 
      112, 
      117, 
      122, 
      128, 
      134, 
      140, 
      147, 
      154, 
      162, 
      170, 
      177, 
      185, 
      192, 
      200, 
      207, 
      215, 
      222, 
      229, 
      236, 
      243, 
      250, 
      257
    ], 
    "IOB": [
      137, 
      131, 
      124, 
      116, 
      107, 
      98, 
      88, 
      77, 
      65, 
      53, 
      42, 
      39, 
      39
    ]
  }, 
  "rate": 0.825, 
  "reason": "COB: 80, Dev: 43, BGI: -12.68, ISF: 82, Target: 80; Eventual BG 172 >= 80, temp 0.775<0.825U/hr", 
  "COB": 80, 
  "eventualBG": 172, 
  "duration": 30, 
  "tick": -3, 
  "IOB": 2.699
}