{
  "bg": 71, 
  "temp": "absolute", 
  "snoozeBG": 65, 
  "predBGs": {
    "COB": [
      71, 
      69, 
      67, 
      64, 
      60, 
      56, 
      51, 
      45, 
      39, 
      39, 
      39, 
      39, 
      39, 
      39, 
      39, 
      39, 
      39, 
      39, 
      39, 
      39, 
      39, 
      39, 
      39, 
      39, 
      39, 
      39, 
      39, 
      39, 
      39, 
      39, 
      39, 
      39, 
      39, 
      39, 
      39, 
      39, 
      39, 
      39, 
      39, 
      39, 
      39, 
      41, 
      44
    ], 
    "aCOB": [
      71, 
      75, 
      79, 
      81, 
      83, 
      84, 
      84, 
      83, 
      82, 
      80, 
      78, 
      77, 
      76, 
      76, 
      76, 
      76, 
      77, 
      78, 
      79, 
      81, 
      83, 
      85, 
      88, 
      91, 
      95, 
      98, 
      102, 
      107, 
      112, 
      117, 
      122, 
      127, 
      132, 
      136, 
      140, 
      145, 
      149, 
      153, 
      156, 
      160, 
      163, 
      166, 
      169
    ], 
    "IOB": [
      71, 
      69, 
      66, 
      62, 
      57, 
      51, 
      45, 
      39, 
      39, 
      39, 
      39, 
      39, 
      39
    ]
  }, 
  "rate": 0, 
  "reason": "COB: 35, Dev: 5, BGI: -5.6, ISF: 82, Target: 96; BG 71<73", 
  "COB": 35, 
  "eventualBG": 44, 
  "duration": 30, 
  "tick": -3, 
  "IOB": 2.117
}