[
  {
    "created_at": "2017-02-28T08:16:34.918Z", 
    "mmtune": {
      "scanDetails": [
        [
          null, 
          0, 
          -75.4
        ]
      ], 
      "timestamp": "2017-02-28T08:16:20.884Z"
    }, 
    "pump": {
      "battery": {
        "status": "normal", 
        "voltage": 1.53
      }, 
      "status": {
        "status": "normal", 
        "timestamp": "2017-02-28T08:12:35.511Z", 
        "bolusing": false, 
        "suspended": false
      }, 
      "reservoir": 107.775, 
      "clock": "2017-02-28T00:13:02-08:00"
    }, 
    "openaps": {
      "suggested": {
        "bg": 206, 
        "temp": "absolute", 
        "snoozeBG": 41, 
        "timestamp": "2017-02-28T08:16:13.054Z", 
        "predBGs": {
          "IOB": [
            206, 
            180, 
            156, 
            134, 
            113, 
            94, 
            76, 
            60, 
            46, 
            39, 
            39, 
            39, 
            39
          ]
        }, 
        "reason": "COB: 0, Dev: -40, BGI: -10.41, ISF: 83, Target: 80; Eventual BG 4 < 80, setting -0.7U/hr, but 30m left and 0 ~ req 0U/hr: no action required", 
        "COB": 0, 
        "eventualBG": 4, 
        "tick": -27, 
        "IOB": 1.958
      }, 
      "iob": {
        "netbasalinsulin": 3.65, 
        "timestamp": "2017-02-28T08:13:02.000Z", 
        "activity": 0.0252, 
        "basaliob": 1.617, 
        "hightempinsulin": 3.7, 
        "bolussnooze": 0.299, 
        "iob": 1.958
      }, 
      "enacted": {
        "bg": 238, 
        "temp": "absolute", 
        "snoozeBG": 150, 
        "recieved": true, 
        "reason": "COB: 6, Dev: 53, BGI: -10.88, ISF: 82, Target: 96; Eventual BG 150 >= 96, temp 2.4<2.6U/hr", 
        "rate": 2.6, 
        "COB": 6, 
        "eventualBG": 150, 
        "timestamp": "2017-02-28T07:59:29.542Z", 
        "duration": 30, 
        "tick": -2, 
        "IOB": 1.718
      }
    }, 
    "uploader": {
      "battery": 70, 
      "batteryVoltage": 3877
    }, 
    "device": "openaps://indy-ex2", 
    "_id": "58b531e2233dd6771ba8969b"
  }
]