{
  "bg": 120, 
  "temp": "absolute", 
  "snoozeBG": 67, 
  "recieved": true, 
  "predBGs": {
    "aCOB": [
      120, 
      128, 
      136, 
      143, 
      151, 
      158, 
      165, 
      171, 
      177, 
      183, 
      188, 
      193, 
      197, 
      201, 
      204, 
      208, 
      211, 
      213, 
      216, 
      219, 
      221, 
      223, 
      225, 
      227, 
      228, 
      230, 
      231, 
      233, 
      234, 
      235, 
      236, 
      237, 
      237, 
      238
    ], 
    "IOB": [
      120, 
      118, 
      117, 
      115, 
      114, 
      112, 
      111, 
      109, 
      107, 
      105, 
      103, 
      101, 
      99, 
      96, 
      94, 
      91, 
      89, 
      86, 
      84, 
      82, 
      80, 
      78, 
      76, 
      74, 
      72, 
      71, 
      69, 
      68, 
      67, 
      66, 
      66, 
      65
    ]
  }, 
  "reason": "COB: 21, Dev: -12, BGI: 0.74, ISF: 82, Target: 96; Eventual BG 67 < 96, setting -0.775U/hr", 
  "rate": 0.0, 
  "COB": 21, 
  "eventualBG": 67, 
  "timestamp": "2017-03-03T16:44:01.685499", 
  "duration": 30, 
  "tick": -2, 
  "IOB": 0.506
}