{
  "device": "openaps://indy-ex2", 
  "pump": {
    "battery": {
      "status": "normal", 
      "voltage": 1.55
    }, 
    "status": {
      "status": "normal", 
      "timestamp": "2017-03-05T13:54:29.716Z", 
      "bolusing": false, 
      "suspended": false
    }, 
    "reservoir": 52.525, 
    "clock": "2017-03-05T05:54:53-08:00"
  }, 
  "uploader": {
    "battery": 69, 
    "batteryVoltage": 3873
  }, 
  "openaps": {
    "suggested": {
      "bg": 147, 
      "temp": "absolute", 
      "snoozeBG": 130, 
      "timestamp": "2017-03-05T13:58:11.378Z", 
      "predBGs": {
        "IOB": [
          147, 
          147, 
          146, 
          146, 
          145, 
          144, 
          143, 
          142, 
          141, 
          139, 
          137, 
          135, 
          132, 
          129, 
          127, 
          124, 
          122, 
          119, 
          117, 
          115, 
          113, 
          110, 
          108, 
          107, 
          105, 
          103, 
          102, 
          100, 
          99, 
          98, 
          97, 
          96, 
          95, 
          95, 
          94, 
          94, 
          93
        ]
      }, 
      "reason": "COB: 0, Dev: 17, BGI: -2.9, ISF: 82, Target: 96; Eventual BG 130 >= 96, temp 1.35<1.45U/hr, but 29m left and 1.35 ~ req 1.45U/hr: no action required", 
      "COB": 0, 
      "eventualBG": 130, 
      "tick": "+1", 
      "IOB": 0.415
    }, 
    "iob": {
      "netbasalinsulin": 1.15, 
      "timestamp": "2017-03-05T13:54:53.000Z", 
      "activity": 0.0071, 
      "basaliob": 0.415, 
      "hightempinsulin": 1.25, 
      "bolussnooze": 0, 
      "iob": 0.415
    }, 
    "enacted": {
      "bg": 149, 
      "temp": "absolute", 
      "snoozeBG": 131, 
      "recieved": true, 
      "rate": 1.4, 
      "reason": "COB: 0, Dev: 17, BGI: -3.39, ISF: 82, Target: 96; Eventual BG 131 >= 96, temp 1.05<1.4U/hr", 
      "COB": 0, 
      "eventualBG": 131, 
      "timestamp": "2017-03-05T13:31:14.205Z", 
      "duration": 30, 
      "tick": "+2", 
      "IOB": 0.422
    }
  }, 
  "mmtune": {
    "scanDetails": [
      [
        null, 
        0, 
        -75.4
      ]
    ], 
    "timestamp": "2017-03-05T13:58:19.488Z"
  }
}