{
  "device": "openaps://indy-ex2", 
  "pump": {
    "battery": {
      "status": "normal", 
      "voltage": 1.47
    }, 
    "status": {
      "status": "normal", 
      "timestamp": "2017-01-04T00:30:51.689Z", 
      "bolusing": false, 
      "suspended": false
    }, 
    "reservoir": 130.6, 
    "clock": "2017-01-03T16:30:56-08:00"
  }, 
  "uploader": {
    "battery": 90, 
    "batteryVoltage": 4079
  }, 
  "openaps": {
    "suggested": {
      "bg": 102, 
      "temp": "absolute", 
      "snoozeBG": 130, 
      "timestamp": "2017-01-04T00:35:13.152Z", 
      "predBGs": {
        "COB": [
          102, 
          104, 
          107, 
          110, 
          113, 
          116, 
          120, 
          123, 
          126, 
          129, 
          132, 
          135, 
          138, 
          140, 
          142, 
          144, 
          146, 
          148, 
          149, 
          150, 
          151, 
          152, 
          154, 
          155, 
          156, 
          157, 
          158, 
          159, 
          160, 
          161, 
          163, 
          164, 
          165, 
          167, 
          168, 
          170, 
          171, 
          173, 
          175, 
          177, 
          179, 
          180, 
          182
        ], 
        "aCOB": [
          102, 
          111, 
          120, 
          129, 
          138, 
          147, 
          155, 
          164, 
          171, 
          179, 
          186, 
          192, 
          198, 
          204, 
          209, 
          214, 
          218, 
          221, 
          224, 
          227, 
          229, 
          231, 
          232, 
          234, 
          235, 
          235, 
          236, 
          236, 
          236, 
          235, 
          235, 
          234, 
          233, 
          233, 
          232, 
          232, 
          231
        ], 
        "IOB": [
          102, 
          104, 
          107, 
          109, 
          111, 
          113, 
          115, 
          117, 
          118, 
          119, 
          120, 
          120, 
          120, 
          120, 
          120, 
          119, 
          118, 
          118, 
          117, 
          115, 
          114, 
          113, 
          111, 
          110, 
          109, 
          108, 
          107, 
          105, 
          104, 
          104, 
          103, 
          102, 
          101, 
          101, 
          100, 
          100, 
          100, 
          99
        ]
      }, 
      "reason": "COB: 18, Dev: 18, BGI: -0.49, ISF: 82, Target: 96; Eventual BG 182 >= 96, temp 1.375<1.5U/hr, but 28m left and 1.375 ~ req 1.5U/hr: no action required", 
      "COB": 18, 
      "eventualBG": 182, 
      "tick": "+4", 
      "IOB": -0.118
    }, 
    "iob": {
      "netbasalinsulin": 0.7, 
      "timestamp": "2017-01-04T00:30:56.000Z", 
      "activity": 0.0012, 
      "basaliob": -0.118, 
      "hightempinsulin": 1.25, 
      "bolussnooze": 0, 
      "iob": -0.118
    }, 
    "enacted": {
      "bg": 91, 
      "temp": "absolute", 
      "snoozeBG": 110, 
      "recieved": true, 
      "rate": 0.975, 
      "reason": "COB: 14, Dev: 7, BGI: -1.27, ISF: 82, Target: 96; Eventual BG 141 >= 96, temp 0.8<0.975U/hr", 
      "COB": 14, 
      "eventualBG": 141, 
      "timestamp": "2017-01-04T00:28:23.078Z", 
      "duration": 30, 
      "tick": "+2", 
      "IOB": -0.148
    }
  }, 
  "mmtune": {
    "scanDetails": [
      [
        null, 
        0, 
        -65.8
      ]
    ], 
    "timestamp": "2017-01-04T00:35:21.062Z"
  }
}