{
  "device": "openaps://indy-ex2", 
  "pump": {
    "battery": {
      "status": "normal", 
      "voltage": 1.45
    }, 
    "status": {
      "status": "normal", 
      "timestamp": "2017-01-27T03:37:17.750Z", 
      "bolusing": false, 
      "suspended": false
    }, 
    "reservoir": 9.975, 
    "clock": "2017-01-26T19:37:31-08:00"
  }, 
  "uploader": {
    "battery": 78, 
    "batteryVoltage": 3958
  }, 
  "openaps": {
    "suggested": {
      "bg": 158, 
      "temp": "absolute", 
      "snoozeBG": 60, 
      "timestamp": "2017-01-27T03:40:55.633Z", 
      "reason": "COB: 11, Dev: 4, BGI: -4.59, ISF: 90, Target: 100; Eventual BG 66 < 100, setting -0.875U/hr", 
      "rate": 0, 
      "COB": 11, 
      "eventualBG": 66, 
      "duration": 30, 
      "tick": -4, 
      "IOB": 1.24
    }, 
    "iob": {
      "netbasalinsulin": 1.9, 
      "timestamp": "2017-01-27T03:37:31.000Z", 
      "activity": 0.0102, 
      "basaliob": 1.235, 
      "hightempinsulin": 1.9, 
      "bolussnooze": 0, 
      "iob": 1.24
    }, 
    "enacted": {
      "bg": 158, 
      "temp": "absolute", 
      "snoozeBG": 60, 
      "recieved": true, 
      "predBGs": {
        "COB": [
          158, 
          154, 
          150, 
          146, 
          142, 
          138, 
          133, 
          128, 
          123, 
          118, 
          113, 
          108, 
          103, 
          98, 
          93, 
          89, 
          85, 
          81, 
          78, 
          75, 
          72, 
          70, 
          68, 
          66, 
          64, 
          63, 
          62, 
          61, 
          61, 
          60, 
          60, 
          60, 
          61, 
          61, 
          61, 
          62, 
          63, 
          63, 
          64, 
          64, 
          65, 
          65, 
          66
        ], 
        "aCOB": [
          158, 
          163, 
          167, 
          171, 
          175, 
          177, 
          179, 
          181, 
          181, 
          181, 
          181, 
          180, 
          178, 
          176, 
          174, 
          172, 
          170, 
          167, 
          165, 
          162, 
          159, 
          156, 
          153, 
          151, 
          149, 
          147, 
          145, 
          144, 
          143, 
          142, 
          141, 
          141, 
          141, 
          140
        ], 
        "IOB": [
          158, 
          154, 
          150, 
          146, 
          142, 
          137, 
          132, 
          127, 
          122, 
          116, 
          110, 
          105, 
          99, 
          94, 
          89, 
          84, 
          79, 
          75, 
          71, 
          67, 
          64, 
          61, 
          58, 
          56, 
          54, 
          52, 
          50, 
          49, 
          48, 
          47, 
          46, 
          46, 
          46, 
          46, 
          45
        ]
      }, 
      "rate": 0, 
      "reason": "COB: 11, Dev: 4, BGI: -4.59, ISF: 90, Target: 100; Eventual BG 66 < 100, setting -0.875U/hr", 
      "COB": 11, 
      "eventualBG": 66, 
      "timestamp": "2017-01-27T03:42:25.124Z", 
      "duration": 30, 
      "tick": -4, 
      "IOB": 1.24
    }
  }, 
  "mmtune": {
    "scanDetails": [
      [
        null, 
        0, 
        -57
      ]
    ], 
    "timestamp": "2017-01-27T03:42:32.974Z"
  }
}