{
  "device": "openaps://indy-ex2", 
  "pump": {
    "battery": {
      "status": "normal", 
      "voltage": 1.5
    }, 
    "status": {
      "status": "normal", 
      "timestamp": "2017-01-02T19:02:25.647Z", 
      "bolusing": false, 
      "suspended": false
    }, 
    "reservoir": 92.2, 
    "clock": "2017-01-02T11:02:29-08:00"
  }, 
  "uploader": {
    "battery": 72, 
    "batteryVoltage": 3898
  }, 
  "openaps": {
    "suggested": {
      "bg": 155, 
      "temp": "absolute", 
      "snoozeBG": 109, 
      "timestamp": "2017-01-02T19:05:01.019Z", 
      "predBGs": {
        "IOB": [
          155, 
          151, 
          147, 
          144, 
          140, 
          137, 
          133, 
          130, 
          127, 
          124, 
          122, 
          119, 
          117, 
          115, 
          114, 
          112, 
          111, 
          110, 
          109, 
          109, 
          108, 
          108, 
          108, 
          107, 
          107, 
          107, 
          107, 
          107, 
          107, 
          107, 
          107, 
          108
        ]
      }, 
      "reason": "COB: 0, Dev: 10, BGI: -5.35, ISF: 90, Target: 100; Eventual BG 109 >= 100, temp 0.675 >~ req 0.675U/hr", 
      "COB": 0, 
      "eventualBG": 109, 
      "tick": -2, 
      "IOB": 0.619
    }, 
    "iob": {
      "netbasalinsulin": 1.4, 
      "timestamp": "2017-01-02T19:02:29.000Z", 
      "activity": 0.0119, 
      "basaliob": 0.584, 
      "hightempinsulin": 1.45, 
      "bolussnooze": 0, 
      "iob": 0.619
    }, 
    "enacted": {
      "bg": 169, 
      "temp": "absolute", 
      "snoozeBG": 94, 
      "recieved": true, 
      "rate": 0.35, 
      "reason": "COB: 0, Dev: 4, BGI: -5.62, ISF: 90, Target: 100; Eventual BG 94 < 100, Snooze BG 94, setting 0.35U/hr", 
      "COB": 0, 
      "eventualBG": 94, 
      "timestamp": "2017-01-02T18:49:34.578Z", 
      "duration": 30, 
      "tick": -5, 
      "IOB": 0.877
    }
  }, 
  "mmtune": {
    "scanDetails": [
      [
        null, 
        0, 
        -62.4
      ]
    ], 
    "timestamp": "2017-01-02T19:05:13.059Z"
  }
}