{
  "device": "openaps://indy-ex2", 
  "pump": {
    "battery": {
      "status": "normal", 
      "voltage": 1.41
    }, 
    "status": {
      "status": "normal", 
      "timestamp": "2017-02-24T19:15:02.108Z", 
      "bolusing": false, 
      "suspended": false
    }, 
    "reservoir": 121.6, 
    "clock": "2017-02-24T11:15:17-08:00"
  }, 
  "uploader": {
    "battery": 66, 
    "batteryVoltage": 3839
  }, 
  "openaps": {
    "suggested": {
      "bg": 161, 
      "temp": "absolute", 
      "snoozeBG": 34, 
      "timestamp": "2017-02-24T19:18:45.031Z", 
      "reason": "COB: 0, Dev: -19, BGI: -5.52, ISF: 82, Target: 80; Eventual BG 34 < 80, setting -1.6U/hr", 
      "rate": 0, 
      "COB": 0, 
      "eventualBG": 34, 
      "duration": 30, 
      "tick": -11, 
      "IOB": 1.325
    }, 
    "iob": {
      "netbasalinsulin": 2.1, 
      "timestamp": "2017-02-24T19:15:17.000Z", 
      "activity": 0.0135, 
      "basaliob": 1.325, 
      "hightempinsulin": 2.2, 
      "bolussnooze": 0, 
      "iob": 1.325
    }, 
    "enacted": {
      "bg": 161, 
      "temp": "absolute", 
      "snoozeBG": 34, 
      "recieved": true, 
      "predBGs": {
        "IOB": [
          161, 
          150, 
          140, 
          130, 
          121, 
          111, 
          103, 
          95, 
          87, 
          80, 
          73, 
          67, 
          61, 
          56, 
          51, 
          47, 
          43, 
          39
        ]
      }, 
      "rate": 0, 
      "reason": "COB: 0, Dev: -19, BGI: -5.52, ISF: 82, Target: 80; Eventual BG 34 < 80, setting -1.6U/hr", 
      "COB": 0, 
      "eventualBG": 34, 
      "timestamp": "2017-02-24T19:20:01.562Z", 
      "duration": 30, 
      "tick": -11, 
      "IOB": 1.325
    }
  }, 
  "mmtune": {
    "scanDetails": [
      [
        null, 
        0, 
        -58.2
      ]
    ], 
    "timestamp": "2017-02-24T19:20:13.442Z"
  }
}