{
  "device": "openaps://indy-ex2", 
  "pump": {
    "battery": {
      "status": "normal", 
      "voltage": 1.43
    }, 
    "status": {
      "status": "normal", 
      "timestamp": "2017-02-19T02:43:33.245Z", 
      "bolusing": false, 
      "suspended": false
    }, 
    "reservoir": 80.9, 
    "clock": "2017-02-18T18:43:56-08:00"
  }, 
  "uploader": {
    "battery": 69, 
    "batteryVoltage": 3868
  }, 
  "openaps": {
    "suggested": {
      "bg": 145, 
      "temp": "absolute", 
      "snoozeBG": 102, 
      "timestamp": "2017-02-19T02:46:14.417Z", 
      "reason": "COB: 0, Dev: 9, BGI: -4.69, ISF: 95, Target: 80; Eventual BG 102 >= 80, temp 0.45<0.9U/hr", 
      "rate": 0.9, 
      "COB": 0, 
      "eventualBG": 102, 
      "duration": 30, 
      "tick": -3, 
      "IOB": 0.545
    }, 
    "iob": {
      "netbasalinsulin": 2.25, 
      "timestamp": "2017-02-19T02:43:56.000Z", 
      "activity": 0.0099, 
      "basaliob": 0.545, 
      "hightempinsulin": 2.4, 
      "bolussnooze": 0, 
      "iob": 0.545
    }, 
    "enacted": {
      "bg": 145, 
      "temp": "absolute", 
      "snoozeBG": 102, 
      "recieved": true, 
      "predBGs": {
        "IOB": [
          145, 
          142, 
          139, 
          136, 
          133, 
          131, 
          128, 
          126, 
          123, 
          121, 
          119, 
          116, 
          114, 
          112, 
          111, 
          109, 
          108, 
          107, 
          106, 
          105, 
          105, 
          104, 
          103, 
          103, 
          103, 
          102
        ]
      }, 
      "rate": 0.9, 
      "reason": "COB: 0, Dev: 9, BGI: -4.69, ISF: 95, Target: 80; Eventual BG 102 >= 80, temp 0.45<0.9U/hr", 
      "COB": 0, 
      "eventualBG": 102, 
      "timestamp": "2017-02-19T02:47:16.108Z", 
      "duration": 30, 
      "tick": -3, 
      "IOB": 0.545
    }
  }, 
  "mmtune": {
    "scanDetails": [
      [
        null, 
        0, 
        -81.6
      ]
    ], 
    "timestamp": "2017-02-19T02:47:23.968Z"
  }
}