{
  "device": "openaps://indy-ex2", 
  "pump": {
    "battery": {
      "status": "normal", 
      "voltage": 1.57
    }, 
    "status": {
      "status": "normal", 
      "timestamp": "2017-01-03T10:35:56.029Z", 
      "bolusing": false, 
      "suspended": false
    }, 
    "reservoir": 68.925, 
    "clock": "2017-01-03T02:36:00-08:00"
  }, 
  "uploader": {
    "battery": 69, 
    "batteryVoltage": 3869
  }, 
  "openaps": {
    "suggested": {
      "bg": 148, 
      "temp": "absolute", 
      "snoozeBG": 117, 
      "timestamp": "2017-01-03T10:39:57.442Z", 
      "predBGs": {
        "IOB": [
          148, 
          147, 
          145, 
          144, 
          142, 
          140, 
          138, 
          136, 
          134, 
          132, 
          130, 
          127, 
          125, 
          123, 
          121, 
          119, 
          117, 
          116, 
          114, 
          113, 
          111, 
          110, 
          110, 
          109, 
          108, 
          108, 
          107, 
          107, 
          106, 
          106, 
          106, 
          106, 
          105
        ]
      }, 
      "reason": "COB: 0, Dev: 13, BGI: -3.27, ISF: 82, Target: 96; Eventual BG 117 >= 96, temp 1.05<1.1U/hr, but 28m left and 1.05 ~ req 1.1U/hr: no action required", 
      "COB": 0, 
      "eventualBG": 117, 
      "tick": -1, 
      "IOB": 0.532
    }, 
    "iob": {
      "netbasalinsulin": 1.4, 
      "timestamp": "2017-01-03T10:36:00.000Z", 
      "activity": 0.008, 
      "basaliob": 0.532, 
      "hightempinsulin": 1.5, 
      "bolussnooze": 0, 
      "iob": 0.532
    }, 
    "enacted": {
      "bg": 150, 
      "temp": "absolute", 
      "snoozeBG": 115, 
      "recieved": true, 
      "rate": 1, 
      "reason": "COB: 0, Dev: 13, BGI: -3.44, ISF: 82, Target: 96; Eventual BG 115 >= 96, temp 0<1U/hr", 
      "COB": 0, 
      "eventualBG": 115, 
      "timestamp": "2017-01-03T10:21:22.421Z", 
      "duration": 30, 
      "tick": "+5", 
      "IOB": 0.586
    }
  }, 
  "mmtune": {
    "scanDetails": [
      [
        null, 
        0, 
        -88.4
      ]
    ], 
    "timestamp": "2017-01-03T10:40:09.322Z"
  }
}